{"name":"build-javascript","namedChunkGroups":{"polyfill":{"name":"polyfill","assets":[{"name":"webpack-runtime-97c739b2b3a46d664d59.js","size":4413},{"name":"polyfill-afe370c024e73666ef83.js","size":85029}],"filteredAssets":0,"assetsSize":89442,"filteredAuxiliaryAssets":2,"auxiliaryAssetsSize":228653},"app":{"name":"app","assets":[{"name":"webpack-runtime-97c739b2b3a46d664d59.js","size":4413},{"name":"styles.1ed881dbf7e76156af57.css","size":991},{"name":"framework-72fb217890867ca66df6.js","size":140556},{"name":"app-b1f1a7608982a0676030.js","size":76821}],"filteredAssets":0,"assetsSize":222781,"filteredAuxiliaryAssets":3,"auxiliaryAssetsSize":692465},"component---src-pages-404-tsx":{"name":"component---src-pages-404-tsx","assets":[{"name":"styles.1ed881dbf7e76156af57.css","size":991},{"name":"component---src-pages-404-tsx-cc12690ce451d22a5606.js","size":1181}],"filteredAssets":0,"assetsSize":2172,"filteredAuxiliaryAssets":1,"auxiliaryAssetsSize":2859},"component---src-pages-docs-tsx":{"name":"component---src-pages-docs-tsx","assets":[{"name":"styles.1ed881dbf7e76156af57.css","size":991},{"name":"component---src-pages-docs-tsx-c76e12ae9436f78387ab.js","size":1182}],"filteredAssets":0,"assetsSize":2173,"filteredAuxiliaryAssets":1,"auxiliaryAssetsSize":2883},"component---src-pages-index-tsx":{"name":"component---src-pages-index-tsx","assets":[{"name":"styles.1ed881dbf7e76156af57.css","size":991},{"name":"component---src-pages-index-tsx-34ebffd95930f8540c78.js","size":1226}],"filteredAssets":0,"assetsSize":2217,"filteredAuxiliaryAssets":1,"auxiliaryAssetsSize":2919}},"assetsByChunkName":{"polyfill":["webpack-runtime-97c739b2b3a46d664d59.js","polyfill-afe370c024e73666ef83.js"],"app":["webpack-runtime-97c739b2b3a46d664d59.js","styles.1ed881dbf7e76156af57.css","framework-72fb217890867ca66df6.js","app-b1f1a7608982a0676030.js"],"component---src-pages-404-tsx":["styles.1ed881dbf7e76156af57.css","component---src-pages-404-tsx-cc12690ce451d22a5606.js"],"component---src-pages-docs-tsx":["styles.1ed881dbf7e76156af57.css","component---src-pages-docs-tsx-c76e12ae9436f78387ab.js"],"component---src-pages-index-tsx":["styles.1ed881dbf7e76156af57.css","component---src-pages-index-tsx-34ebffd95930f8540c78.js"]},"childAssetsByChunkName":{}}