{"name":"build-javascript","namedChunkGroups":{"polyfill":{"name":"polyfill","assets":[{"name":"webpack-runtime-e57bc052832a1b69564e.js","size":4481},{"name":"polyfill-afe370c024e73666ef83.js","size":85029}],"filteredAssets":0,"assetsSize":89510,"filteredAuxiliaryAssets":2,"auxiliaryAssetsSize":228757},"app":{"name":"app","assets":[{"name":"webpack-runtime-e57bc052832a1b69564e.js","size":4481},{"name":"styles.a6792d5ac8dcd90de231.css","size":1183},{"name":"framework-72fb217890867ca66df6.js","size":140556},{"name":"app-ddb642a8b22b966b582e.js","size":76931}],"filteredAssets":0,"assetsSize":223151,"filteredAuxiliaryAssets":3,"auxiliaryAssetsSize":692753},"component---src-pages-404-tsx":{"name":"component---src-pages-404-tsx","assets":[{"name":"styles.a6792d5ac8dcd90de231.css","size":1183},{"name":"component---src-pages-404-tsx-0c27e1b2dae7db7bbbe4.js","size":2783}],"filteredAssets":0,"assetsSize":3966,"filteredAuxiliaryAssets":1,"auxiliaryAssetsSize":5399},"component---src-pages-docs-tsx":{"name":"component---src-pages-docs-tsx","assets":[{"name":"styles.a6792d5ac8dcd90de231.css","size":1183},{"name":"component---src-pages-docs-tsx-89b0b12e86273140c2d2.js","size":2779}],"filteredAssets":0,"assetsSize":3962,"filteredAuxiliaryAssets":1,"auxiliaryAssetsSize":5417},"component---src-pages-examples-tsx":{"name":"component---src-pages-examples-tsx","assets":[{"name":"styles.a6792d5ac8dcd90de231.css","size":1183},{"name":"component---src-pages-examples-tsx-959f2d5f3371d78fb3a9.js","size":2782}],"filteredAssets":0,"assetsSize":3965,"filteredAuxiliaryAssets":1,"auxiliaryAssetsSize":5403},"component---src-pages-index-tsx":{"name":"component---src-pages-index-tsx","assets":[{"name":"styles.a6792d5ac8dcd90de231.css","size":1183},{"name":"component---src-pages-index-tsx-71a45ecf401fc355ed47.js","size":2804}],"filteredAssets":0,"assetsSize":3987,"filteredAuxiliaryAssets":1,"auxiliaryAssetsSize":5414}},"assetsByChunkName":{"polyfill":["webpack-runtime-e57bc052832a1b69564e.js","polyfill-afe370c024e73666ef83.js"],"app":["webpack-runtime-e57bc052832a1b69564e.js","styles.a6792d5ac8dcd90de231.css","framework-72fb217890867ca66df6.js","app-ddb642a8b22b966b582e.js"],"component---src-pages-404-tsx":["styles.a6792d5ac8dcd90de231.css","component---src-pages-404-tsx-0c27e1b2dae7db7bbbe4.js"],"component---src-pages-docs-tsx":["styles.a6792d5ac8dcd90de231.css","component---src-pages-docs-tsx-89b0b12e86273140c2d2.js"],"component---src-pages-examples-tsx":["styles.a6792d5ac8dcd90de231.css","component---src-pages-examples-tsx-959f2d5f3371d78fb3a9.js"],"component---src-pages-index-tsx":["styles.a6792d5ac8dcd90de231.css","component---src-pages-index-tsx-71a45ecf401fc355ed47.js"]},"childAssetsByChunkName":{}}